[
  {
    "id": "algorithm\\data-structures\\graph\\dijkstra",
    "title": "다익스트라 (dijkstra)",
    "url": "/samidare20/docs/algorithm\\data-structures\\graph\\dijkstra"
  },
  {
    "id": "algorithm\\data-structures\\graph\\Floyd-Warshall",
    "title": "플로이드-워셜 (Floyd-Warshall)",
    "url": "/samidare20/docs/algorithm\\data-structures\\graph\\Floyd-Warshall"
  },
  {
    "id": "intro",
    "title": "시작하기",
    "url": "/samidare20/docs/intro"
  },
  {
    "id": "utils\\Beautify\\bash",
    "title": "bash",
    "url": "/samidare20/docs/utils\\Beautify\\bash"
  },
  {
    "id": "utils\\Beautify\\docusaurus",
    "title": "docusaurus",
    "url": "/samidare20/docs/utils\\Beautify\\docusaurus"
  },
  {
    "id": "utils\\github\\alias",
    "title": "alias",
    "url": "/samidare20/docs/utils\\github\\alias"
  },
  {
    "id": "utils\\github\\stash",
    "title": "stash",
    "url": "/samidare20/docs/utils\\github\\stash"
  }
]